indic_transliteration/__init__.py
indic_transliteration/aksharamukha_helper.py
indic_transliteration/deduplication.py
indic_transliteration/detect.py
indic_transliteration/roman_numerals.py
indic_transliteration/sacred_texts_scheme.py
indic_transliteration/tamil_tools.py
indic_transliteration/vidyut_helper.py
indic_transliteration/font_converter/__init__.py
indic_transliteration/font_converter/krutidev2unicode.py
indic_transliteration/font_converter/tech_hindi/__init__.py
indic_transliteration/sanscript/__init__.py
indic_transliteration/sanscript/brahmic_mapper.py
indic_transliteration/sanscript/roman_mapper.py
indic_transliteration/sanscript/schemes/__init__.py
indic_transliteration/sanscript/schemes/migrator.py
indic_transliteration/sanscript/schemes/roman.py
indic_transliteration/sanscript/schemes/brahmic/__init__.py
indic_transliteration/sanscript/schemes/brahmic/accent.py
indic_transliteration/sanscript/schemes/data/.git
indic_transliteration/sanscript/schemes/data/LICENSE
indic_transliteration/sanscript/schemes/data/README.md
indic_transliteration/sanscript/schemes/data/_devanagari_vowel_to_marks.toml
indic_transliteration/sanscript/schemes/data/language_code_to_script.json
indic_transliteration/sanscript/schemes/data/package-lock.json
indic_transliteration/sanscript/schemes/data/package.json
indic_transliteration/sanscript/schemes/data/.github/FUNDING.yml
indic_transliteration/sanscript/schemes/data/.github/workflows/check_and_release.yml
indic_transliteration/sanscript/schemes/data/brahmic/ahom.toml
indic_transliteration/sanscript/schemes/data/brahmic/assamese.toml
indic_transliteration/sanscript/schemes/data/brahmic/balinese.toml
indic_transliteration/sanscript/schemes/data/brahmic/bengali.toml
indic_transliteration/sanscript/schemes/data/brahmic/bhaiksuki.toml
indic_transliteration/sanscript/schemes/data/brahmic/brahmi.toml
indic_transliteration/sanscript/schemes/data/brahmic/brahmi_tamil.toml
indic_transliteration-2.3.76.dist-info/licenses/LICENSE.txt
indic_transliteration-2.3.76.dist-info/METADATA
indic_transliteration-2.3.76.dist-info/WHEEL
indic_transliteration-2.3.76.dist-info/entry_points.txt
indic_transliteration-2.3.76.dist-info/top_level.txt
indic_transliteration-2.3.76.dist-info/RECORD
