Metadata-Version: 2.4
Name: indic_transliteration
Version: 2.3.76
Summary: Transliteration tools to convert text in one indic script encoding to another
Home-page: https://github.com/indic-transliteration/indic_transliteration_py
Author: Sanskrit programmers
Author-email: sanskrit-programmers@googlegroups.com
License: MIT
Keywords: indic script transliteration hindi sanskrit samskritam kannada devanagari tamil malayalam telugu gurumukhi gujarati bengali oriya - Harvard-Kyoto IAST Roman-Unicode) SLP1 WX
Classifier: Development Status :: 5 - Production/Stable
Classifier: Intended Audience :: Education
Classifier: Intended Audience :: Science/Research
Classifier: Intended Audience :: Developers
Classifier: Natural Language :: Hindi
Classifier: Natural Language :: Tamil
Classifier: Natural Language :: Bengali
Classifier: Natural Language :: Panjabi
Classifier: Natural Language :: Marathi
Classifier: Topic :: Text Processing :: Linguistic
Classifier: License :: OSI Approved :: MIT License
Classifier: Programming Language :: Python :: 3
License-File: LICENSE.txt
Requires-Dist: backports.functools_lru_cache
Requires-Dist: regex
Requires-Dist: typer
Requires-Dist: toml
Requires-Dist: roman
Provides-Extra: test
Requires-Dist: pytest; extra == "test"
Provides-Extra: extras
Requires-Dist: selenium; extra == "extras"
Requires-Dist: aksharamukha; extra == "extras"
Requires-Dist: vidyut-lipi; extra == "extras"
Dynamic: author
Dynamic: author-email
Dynamic: classifier
Dynamic: home-page
Dynamic: keywords
Dynamic: license
Dynamic: license-file
Dynamic: provides-extra
Dynamic: requires-dist
Dynamic: summary
